BinToGene/__init__.py
BinToGene/bin.py
BinToGene/bin_to_gene.py
BinToGene/utils.py
BinToGene/images/example.png
BinToGene/resources/__init__.py
BinToGene/resources/cell_by_bin.h5ad
BinToGene/resources/gencode_v34_genes_protein_coding.csv
BinToGene/tests/__init__.py
BinToGene/tests/gencode_example.csv
BinToGene/tests/test_bin.py
BinToGene/tests/test_bin_to_gene.py
BinToGene/tests/test_binary_search.py
BinToGene/tests/test_extend_interval.py
BinToGene-1.23.dist-info/LICENCE
BinToGene-1.23.dist-info/METADATA
BinToGene-1.23.dist-info/WHEEL
BinToGene-1.23.dist-info/top_level.txt
BinToGene-1.23.dist-info/RECORD
