Metadata-Version: 2.1
Name: BinToGene
Version: 1.23
Summary: A bin to gene conversion package.
Home-page: https://github.com/ferrocactus/BinToGene
Author: Euxhen Hasanaj
Author-email: ehasanaj@cs.cmu.edu
License: UNKNOWN
Platform: UNKNOWN
Classifier: Programming Language :: Python :: 3
Classifier: License :: OSI Approved :: MIT License
Classifier: Operating System :: OS Independent
Requires-Python: >=3.7
Requires-Dist: numpy
Requires-Dist: pandas
Requires-Dist: tqdm
